{"cameraMode":{"drawMode":0,"name":"Shaded","section":"Shading Mode"},"sceneLighting":false,"audioPlay":false,"sceneViewState":{"m_AlwaysRefresh":false,"showFog":true,"showSkybox":false,"showFlares":true,"showImageEffects":true,"showParticleSystems":true,"showVisualEffectGraphs":true,"m_FxEnabled":true},"in2DMode":false,"pivot":{"x":-3.038057565689087,"y":-4.163656234741211,"z":-7.363040924072266},"rotation":{"x":0.030296072363853456,"y":-0.9635657072067261,"z":0.23426295816898347,"w":0.1243947222828865},"size":5.680452823638916,"orthographic":false}